__init__.py
app.py
config.py
ingest.py
run_localGPT.py
setup.py
RAGchain/__init__.py
RAGchain/DB/__init__.py
RAGchain/DB/base.py
RAGchain/DB/mongo_db.py
RAGchain/DB/pickle_db.py
RAGchain/benchmark/__init__.py
RAGchain/benchmark/auto.py
RAGchain/benchmark/base.py
RAGchain/benchmark/answer/__init__.py
RAGchain/benchmark/answer/metrics.py
RAGchain/benchmark/dataset/__init__.py
RAGchain/benchmark/dataset/antique.py
RAGchain/benchmark/dataset/asqa.py
RAGchain/benchmark/dataset/base.py
RAGchain/benchmark/dataset/beir.py
RAGchain/benchmark/dataset/dstc11_track5.py
RAGchain/benchmark/dataset/eli5.py
RAGchain/benchmark/dataset/ko_strategy_qa.py
RAGchain/benchmark/dataset/mr_tydi.py
RAGchain/benchmark/dataset/msmarco.py
RAGchain/benchmark/dataset/natural_qa.py
RAGchain/benchmark/dataset/natural_question.py
RAGchain/benchmark/dataset/nfcorpus.py
RAGchain/benchmark/dataset/qasper.py
RAGchain/benchmark/dataset/search_qa.py
RAGchain/benchmark/dataset/strategy_qa.py
RAGchain/benchmark/dataset/triviaqa.py
RAGchain/benchmark/extra/__init__.py
RAGchain/benchmark/extra/search_detector_evaluator.py
RAGchain/benchmark/retrieval/__init__.py
RAGchain/benchmark/retrieval/evaluator.py
RAGchain/benchmark/retrieval/metrics.py
RAGchain/llm/__init__.py
RAGchain/llm/base.py
RAGchain/llm/basic.py
RAGchain/llm/completion.py
RAGchain/llm/rerank.py
RAGchain/llm/visconde.py
RAGchain/pipeline/__init__.py
RAGchain/pipeline/base.py
RAGchain/pipeline/basic.py
RAGchain/pipeline/google_search.py
RAGchain/pipeline/rerank.py
RAGchain/pipeline/visconde.py
RAGchain/preprocess/__init__.py
RAGchain/preprocess/loader/__init__.py
RAGchain/preprocess/loader/dataset_loader.py
RAGchain/preprocess/loader/deepdoctection_loader.py
RAGchain/preprocess/loader/excel_loader.py
RAGchain/preprocess/loader/file_loader.py
RAGchain/preprocess/loader/hwp_loader.py
RAGchain/preprocess/loader/mathpix_markdown_loader.py
RAGchain/preprocess/loader/nougat_pdf_loader.py
RAGchain/preprocess/loader/pdf_link_loader.py
RAGchain-0.2.6.dist-info/LICENSE
RAGchain-0.2.6.dist-info/METADATA
RAGchain-0.2.6.dist-info/WHEEL
RAGchain-0.2.6.dist-info/top_level.txt
RAGchain-0.2.6.dist-info/RECORD
