Metadata-Version: 2.1
Name: RAGchain
Version: 0.2.6
Summary: Build advanced RAG workflows with LLM, compatible with Langchain
Home-page: https://github.com/Marker-Inc-Korea/RAGchain
Author: Marker-Inc
Author-email: vkehfdl1@gmail.com
License: Apache License 2.0
Keywords: RAG,RAGchain,ragchain,LLM,Langchain,DQA,GPT,ODQA
Classifier: Intended Audience :: Developers
Classifier: Intended Audience :: Information Technology
Classifier: Intended Audience :: Science/Research
Classifier: Programming Language :: Python :: 3.8
Classifier: Programming Language :: Python :: 3.9
Classifier: Programming Language :: Python :: 3.10
Classifier: Topic :: Scientific/Engineering :: Artificial Intelligence
Classifier: Topic :: Software Development :: Libraries
Classifier: Topic :: Software Development :: Libraries :: Python Modules
Requires-Python: >=3.8
License-File: LICENSE
Requires-Dist: langchain (>=0.1.0)
Requires-Dist: chromadb (>=0.4.16)
Requires-Dist: urllib3
Requires-Dist: pdfminer.six
Requires-Dist: click
Requires-Dist: openpyxl
Requires-Dist: pinecone-client
Requires-Dist: python-dotenv (==1.0.0)
Requires-Dist: tiktoken
Requires-Dist: rank-bm25
Requires-Dist: numpy
Requires-Dist: pandas
Requires-Dist: pydantic (==1.10.13)
Requires-Dist: tqdm
Requires-Dist: pymongo
Requires-Dist: requests
Requires-Dist: redis
Requires-Dist: aiohttp
Requires-Dist: openai
Requires-Dist: InstructorEmbedding
Requires-Dist: sentence-transformers
Requires-Dist: huggingface-hub
Requires-Dist: transformers
Requires-Dist: torch
Requires-Dist: pyarrow
Requires-Dist: fastparquet
Requires-Dist: ragas
Requires-Dist: datasets
Requires-Dist: lxml
Requires-Dist: sacrebleu
Requires-Dist: scikit-learn
Requires-Dist: boto3
Requires-Dist: evaluate
Requires-Dist: rouge-score
